LICENSE.txt
README.md
setup.cfg
setup.py
nDimensional/__init__.py
nDimensional/add.py
nDimensional/sub.py
nDimensional.egg-info/PKG-INFO
nDimensional.egg-info/SOURCES.txt
nDimensional.egg-info/dependency_links.txt
nDimensional.egg-info/top_level.txt