Metadata-Version: 2.1
Name: nDimensional
Version: 0.0.5
Summary: Core library for nDimensional
Home-page: https://github.com/analytXbook/nd-core-lib
Download-URL: https://github.com/analytXbook/nd-core-lib/archive/refs/tags/0.0.4.tar.gz
Author: nD
Author-email: dev@nd.com
License: MIT
Keywords: nDimensional,nd
Classifier: Development Status :: 3 - Alpha
Classifier: Intended Audience :: Developers
Classifier: Topic :: Software Development :: Build Tools
Classifier: License :: OSI Approved :: MIT License
Classifier: Programming Language :: Python :: 3.8
Classifier: Programming Language :: Python :: 3.9
Classifier: Programming Language :: Python :: 3.10
License-File: LICENSE.txt
